reqsmith/__init__.py
reqsmith/__version__.py
reqsmith/error_handler.py
reqsmith/exceptions.py
reqsmith/logging_config.py
reqsmith/metrics.py
reqsmith/py.typed
reqsmith/ai/__init__.py
reqsmith/ai/assistant.py
reqsmith/ai/gemini_client.py
reqsmith/ai/validators.py
reqsmith/cli/__init__.py
reqsmith/cli/completion.py
reqsmith/cli/config.py
reqsmith/cli/environment.py
reqsmith/cli/help.py
reqsmith/cli/history.py
reqsmith/cli/main.py
reqsmith/cli/request.py
reqsmith/cli/template.py
reqsmith/config/__init__.py
reqsmith/config/settings.py
reqsmith/core/__init__.py
reqsmith/core/cache_manager.py
reqsmith/core/env_manager.py
reqsmith/core/env_utils.py
reqsmith/core/history_manager.py
reqsmith/core/history_retry.py
reqsmith/core/http_client.py
reqsmith/core/request_validator.py
reqsmith/core/template_executor.py
reqsmith/core/template_importer.py
reqsmith/core/template_manager.py
reqsmith/core/variable_substitution.py
reqsmith/formatters/__init__.py
reqsmith/formatters/response_formatter.py
reqsmith/formatters/response_saver.py
reqsmith/formatters/table_formatter.py
reqsmith/storage/__init__.py
reqsmith/storage/disk_manager.py
reqsmith/storage/hybrid_storage.py
reqsmith/storage/memory_cache.py
reqsmith/storage/models.py
reqsmith/storage/operations.py
reqsmith-0.2.2.dist-info/licenses/LICENSE
reqsmith-0.2.2.dist-info/METADATA
reqsmith-0.2.2.dist-info/WHEEL
reqsmith-0.2.2.dist-info/entry_points.txt
reqsmith-0.2.2.dist-info/top_level.txt
reqsmith-0.2.2.dist-info/RECORD
