Metadata-Version: 2.4
Name: reqsmith
Version: 0.2.2
Summary: Command-line API testing tool with hybrid caching and optional AI assistance
Home-page: https://github.com/VesperAkshay/reqsmith
Author: ReqSmith Team
Author-email: ReqSmith Team <team@reqsmith.dev>
Maintainer-email: ReqSmith Team <team@reqsmith.dev>
License:                                  Apache License
Project-URL: Homepage, https://github.com/VesperAkshay/reqsmith
Project-URL: Documentation, https://vesperakshay.github.io/reqsmith/
Project-URL: Repository, https://github.com/VesperAkshay/reqsmith.git
Project-URL: Bug Reports, https://github.com/VesperAkshay/reqsmith/issues
Project-URL: Changelog, https://github.com/VesperAkshay/reqsmith/blob/main/CHANGELOG.md
Keywords: api,testing,cli,http,rest,graphql,automation
Classifier: Development Status :: 4 - Beta
Classifier: Intended Audience :: Developers
Classifier: Intended Audience :: System Administrators
Classifier: Operating System :: OS Independent
Classifier: Programming Language :: Python :: 3
Classifier: Programming Language :: Python :: 3.9
Classifier: Programming Language :: Python :: 3.10
Classifier: Programming Language :: Python :: 3.11
Classifier: Programming Language :: Python :: 3.12
Classifier: Topic :: Software Development :: Testing
Classifier: Topic :: Internet :: WWW/HTTP
Classifier: Topic :: System :: Networking
Classifier: Topic :: Utilities
Classifier: Environment :: Console
Requires-Python: >=3.9
License-File: LICENSE
Requires-Dist: typer>=0.9.0
Requires-Dist: rich>=13.0.0
Requires-Dist: httpx>=0.24.0
Requires-Dist: python-dotenv>=1.0.0
Requires-Dist: google-generativeai>=0.3.0
Requires-Dist: cryptography>=41.0.0
Requires-Dist: pydantic>=2.0.0
Requires-Dist: click>=8.0.0
Provides-Extra: dev
Requires-Dist: pytest>=7.0.0; extra == "dev"
Requires-Dist: pytest-mock>=3.10.0; extra == "dev"
Requires-Dist: pytest-asyncio>=0.21.0; extra == "dev"
Requires-Dist: pytest-cov>=4.0.0; extra == "dev"
Requires-Dist: black>=23.0.0; extra == "dev"
Requires-Dist: flake8>=6.0.0; extra == "dev"
Requires-Dist: mypy>=1.0.0; extra == "dev"
Requires-Dist: isort>=5.12.0; extra == "dev"
Requires-Dist: pre-commit>=3.0.0; extra == "dev"
Provides-Extra: yaml
Requires-Dist: PyYAML>=6.0; extra == "yaml"
Provides-Extra: all
Requires-Dist: PyYAML>=6.0; extra == "all"
Dynamic: author
Dynamic: home-page
Dynamic: license-file
Dynamic: requires-python
